dg_auditwheel/__init__.py
dg_auditwheel/__main__.py
dg_auditwheel/condatools.py
dg_auditwheel/elfutils.py
dg_auditwheel/error.py
dg_auditwheel/genericpkgctx.py
dg_auditwheel/hashfile.py
dg_auditwheel/lddtree.py
dg_auditwheel/libc.py
dg_auditwheel/main.py
dg_auditwheel/main_addtag.py
dg_auditwheel/main_lddtree.py
dg_auditwheel/main_repair.py
dg_auditwheel/main_show.py
dg_auditwheel/musllinux.py
dg_auditwheel/patcher.py
dg_auditwheel/repair.py
dg_auditwheel/tmpdirs.py
dg_auditwheel/tools.py
dg_auditwheel/wheel_abi.py
dg_auditwheel/wheeltools.py
dg_auditwheel/_vendor/__init__.py
dg_auditwheel/_vendor/wheel/LICENSE.txt
dg_auditwheel/_vendor/wheel/__init__.py
dg_auditwheel/_vendor/wheel/pkginfo.py
dg_auditwheel/_vendor/wheel/util.py
dg_auditwheel/_vendor/wheel/wheelfile.py
dg_auditwheel/_vendor/wheel/cli/__init__.py
dg_auditwheel/_vendor/wheel/cli/convert.py
dg_auditwheel/_vendor/wheel/cli/pack.py
dg_auditwheel/_vendor/wheel/cli/unpack.py
dg_auditwheel/policy/__init__.py
dg_auditwheel/policy/external_references.py
dg_auditwheel/policy/manylinux-policy.json
dg_auditwheel/policy/musllinux-policy.json
dg_auditwheel/policy/policy-schema.json
dg_auditwheel/policy/versioned_symbols.py
dg_auditwheel-1.2.0.dist-info/LICENSE
dg_auditwheel-1.2.0.dist-info/METADATA
dg_auditwheel-1.2.0.dist-info/WHEEL
dg_auditwheel-1.2.0.dist-info/entry_points.txt
dg_auditwheel-1.2.0.dist-info/top_level.txt
dg_auditwheel-1.2.0.dist-info/RECORD
