Metadata-Version: 2.1
Name: dg-auditwheel
Version: 1.2.0
Summary: Cross-distribution Linux wheels
Home-page: https://github.com/DeGirum/dg-auditwheel
Author: Robert T. McGibbon
Author-email: rmcgibbo@gmail.com
License: MIT
Platform: UNKNOWN
Classifier: Development Status :: 4 - Beta
Classifier: Environment :: Console
Classifier: Intended Audience :: Developers
Classifier: License :: OSI Approved :: MIT License
Classifier: Operating System :: POSIX :: Linux
Classifier: Programming Language :: Python :: 3
Classifier: Programming Language :: Python :: 3.8
Classifier: Programming Language :: Python :: 3.9
Classifier: Programming Language :: Python :: 3.10
Classifier: Programming Language :: Python :: 3.11
Classifier: Programming Language :: Python :: 3.12
Classifier: Programming Language :: Python :: 3.13
Classifier: Programming Language :: Python :: 3 :: Only
Classifier: Topic :: Software Development
Classifier: Topic :: Software Development :: Build Tools
Classifier: Topic :: Software Development :: Libraries :: Python Modules
Requires-Python: >=3.8
License-File: LICENSE
Requires-Dist: packaging (>=20.9)
Requires-Dist: pyelftools (>=0.24)
Provides-Extra: coverage
Requires-Dist: pytest-cov ; extra == 'coverage'
Requires-Dist: pytest (>=3.4) ; extra == 'coverage'
Requires-Dist: jsonschema ; extra == 'coverage'
Requires-Dist: pypatchelf ; extra == 'coverage'
Requires-Dist: pretend ; extra == 'coverage'
Requires-Dist: docker ; extra == 'coverage'
Provides-Extra: develop
Requires-Dist: pytest (>=3.4) ; extra == 'develop'
Requires-Dist: jsonschema ; extra == 'develop'
Requires-Dist: pypatchelf ; extra == 'develop'
Requires-Dist: pretend ; extra == 'develop'
Requires-Dist: docker ; extra == 'develop'
Requires-Dist: pytest-cov ; extra == 'develop'
Provides-Extra: test
Requires-Dist: pytest (>=3.4) ; extra == 'test'
Requires-Dist: jsonschema ; extra == 'test'
Requires-Dist: pypatchelf ; extra == 'test'
Requires-Dist: pretend ; extra == 'test'
Requires-Dist: docker ; extra == 'test'
